pdpolygonapi/__init__.py
pdpolygonapi/_pdpolygonapi_base.py
pdpolygonapi/pdpolygonapi.py
pdpolygonapi-0.0.2.dist-info/METADATA
pdpolygonapi-0.0.2.dist-info/WHEEL
pdpolygonapi-0.0.2.dist-info/licenses/LICENSE
pdpolygonapi-0.0.2.dist-info/licenses/NOTICE
pdpolygonapi-0.0.2.dist-info/RECORD
