Metadata-Version: 2.1
Name: pdpolygonapi
Version: 0.0.2
Summary: A python API for the polygon.io REST API that returns Pandas objects
Project-URL: Homepage, https://github.com/danielgoldfarb/pdpolygonapi
Project-URL: Bug Tracker, https://github.com/danielgoldfarb/pdpolygonapi/issues
Author-email: Danie Goldfarb <dgoldfarb.github@gmail.com>
License-File: LICENSE
License-File: NOTICE
Classifier: License :: OSI Approved :: Apache Software License
Classifier: Operating System :: OS Independent
Classifier: Programming Language :: Python :: 3
Requires-Python: >=3.7
